codacle_graph_sdk/__init__.py
codacle_graph_sdk/_core/__init__.py
codacle_graph_sdk/_core/_http.py
codacle_graph_sdk/_core/_validation.py
codacle_graph_sdk/clients/__init__.py
codacle_graph_sdk/clients/_async.py
codacle_graph_sdk/clients/_sync.py
codacle_graph_sdk/exceptions/__init__.py
codacle_graph_sdk/exceptions/_base.py
codacle_graph_sdk/exceptions/auth.py
codacle_graph_sdk/exceptions/network.py
codacle_graph_sdk/exceptions/query.py
codacle_graph_sdk/exceptions/resource.py
codacle_graph_sdk/models/__init__.py
codacle_graph_sdk/models/_base.py
codacle_graph_sdk/models/nodes/__init__.py
codacle_graph_sdk/models/nodes/application.py
codacle_graph_sdk/models/nodes/attribute.py
codacle_graph_sdk/models/nodes/class_.py
codacle_graph_sdk/models/nodes/client.py
codacle_graph_sdk/models/nodes/module.py
codacle_graph_sdk/models/nodes/object.py
codacle_graph_sdk/models/nodes/subroutine.py
codacle_graph_sdk/models/relationships/__init__.py
codacle_graph_sdk/models/relationships/hierarchy.py
codacle_graph_sdk/models/relationships/inheritance.py
codacle_graph_sdk/models/relationships/instance.py
codacle_graph_sdk/models/relationships/references.py
codacle_graph_sdk/models/relationships/structure.py
codacle_graph_sdk/models/requests/__init__.py
codacle_graph_sdk/models/requests/admin.py
codacle_graph_sdk/models/requests/bulk.py
codacle_graph_sdk/models/requests/query.py
codacle_graph_sdk/models/responses/__init__.py
codacle_graph_sdk/models/responses/_utils.py
codacle_graph_sdk/models/responses/api_key.py
codacle_graph_sdk/models/responses/bulk.py
codacle_graph_sdk/models/responses/common.py
codacle_graph_sdk/models/responses/credentials.py
codacle_graph_sdk/models/responses/query.py
codacle_graph_sdk/py.typed
codacle_graph_sdk-1.1.1.dist-info/METADATA
codacle_graph_sdk-1.1.1.dist-info/WHEEL
codacle_graph_sdk-1.1.1.dist-info/RECORD
