Metadata-Version: 2.4
Name: codacle-graph-sdk
Version: 1.1.1
Summary: Python SDK for the Codacle Graph Service API
License: MIT
Author: Octavio
Author-email: octaviopavon7@gmail.com
Requires-Python: >=3.10,<4.0
Classifier: Development Status :: 4 - Beta
Classifier: Framework :: Pydantic :: 2
Classifier: License :: OSI Approved :: MIT License
Classifier: Programming Language :: Python :: 3
Classifier: Programming Language :: Python :: 3.10
Classifier: Programming Language :: Python :: 3.11
Classifier: Programming Language :: Python :: 3.12
Classifier: Programming Language :: Python :: 3.13
Classifier: Programming Language :: Python :: 3.14
Classifier: Typing :: Typed
Requires-Dist: httpx (>=0.27.0,<0.28.0)
Requires-Dist: pydantic (>=2.0,<3.0)
Requires-Dist: typing-extensions (>=4.0,<5.0)
Project-URL: Repository, https://github.com/codacle/codacle-graph-sdk
